scythe_cli/__init__.py
scythe_cli/application/__init__.py
scythe_cli/application/application.py
scythe_cli/application/dependencies.py
scythe_cli/application/quickstart.py
scythe_cli/application/stack.py
scythe_cli/application/timers.py
scythe_cli/console.py
scythe_cli/constants.py
scythe_cli/harvest.py
scythe_cli/stack.py
scythe_cli/ui/apps.py
scythe_cli/ui/styles/app.css
scythe_cli/ui/styles/timer-container.css
scythe_cli/ui/styles/timer-modal.css
scythe_cli/ui/styles/timer.css
scythe_cli/ui/widgets/__init__.py
scythe_cli/ui/widgets/actions.py
scythe_cli/ui/widgets/time_display.py
scythe_cli/ui/widgets/timer.py
scythe_cli/ui/widgets/timer_container.py
scythe_cli/ui/widgets/timer_modal.py
scythe_cli/ui/widgets/viewing_day.py
scythe_cli/utils.py
scythe_cli-1.4.2.dist-info/entry_points.txt
scythe_cli-1.4.2.dist-info/WHEEL
scythe_cli-1.4.2.dist-info/METADATA
scythe_cli-1.4.2.dist-info/RECORD
