Metadata-Version: 2.1
Name: scythe-cli
Version: 1.4.2
Summary: A Harvest is always better with a good tool
Home-page: https://github.com/seanrcollings/scythe
License: MIT
Author: Sean Collings
Author-email: me@seancollings.dev
Requires-Python: >=3.10,<4.0
Classifier: License :: OSI Approved :: MIT License
Classifier: Programming Language :: Python :: 3
Classifier: Programming Language :: Python :: 3.10
Classifier: Programming Language :: Python :: 3.11
Requires-Dist: arc-cli (>=8.6.2,<9.0.0)
Requires-Dist: hishel (>=0.0.20,<0.0.21)
Requires-Dist: httpx (>=0.24.0,<0.25.0)
Requires-Dist: keyring (>=23.13.1,<24.0.0)
Requires-Dist: msgspec (>=0.15.1,<0.16.0)
Requires-Dist: requests (>=2.25.1,<3.0.0)
Requires-Dist: textual (>=0.45.1,<0.46.0)
Requires-Dist: xdg (>=5.1.1,<6.0.0)
